datasette_cookies_for_magic_parameters/__init__.py
datasette_cookies_for_magic_parameters-0.1.2.dist-info/LICENSE
datasette_cookies_for_magic_parameters-0.1.2.dist-info/METADATA
datasette_cookies_for_magic_parameters-0.1.2.dist-info/WHEEL
datasette_cookies_for_magic_parameters-0.1.2.dist-info/entry_points.txt
datasette_cookies_for_magic_parameters-0.1.2.dist-info/top_level.txt
datasette_cookies_for_magic_parameters-0.1.2.dist-info/RECORD
