Metadata-Version: 2.1
Name: datasette-cookies-for-magic-parameters
Version: 0.1.2
Summary: UI for setting cookies to populate magic parameters
Home-page: https://github.com/simonw/datasette-cookies-for-magic-parameters
Author: Simon Willison
License: Apache License, Version 2.0
Project-URL: Issues, https://github.com/simonw/datasette-cookies-for-magic-parameters/issues
Project-URL: CI, https://github.com/simonw/datasette-cookies-for-magic-parameters/actions
Project-URL: Changelog, https://github.com/simonw/datasette-cookies-for-magic-parameters/releases
Classifier: Framework :: Datasette
Classifier: License :: OSI Approved :: Apache Software License
Requires-Python: >=3.7
License-File: LICENSE
Requires-Dist: datasette
Provides-Extra: test
Requires-Dist: pytest ; extra == 'test'
Requires-Dist: pytest-asyncio ; extra == 'test'
